{"series_ID": 102, "series_desc": "\nthird week - 29 mehr 1401 - fixed many many things including the targeted backdoor attack, success measures, etc.\n", "log_path": "/content/drive/MyDrive/experiments/IMDB/SVM/102-kkt-imdb-wordcount-60.json", "log": {"model": "SVM", "dataset": "IMDB", "task": "binary classification", "pytorch_seed": 50, "numpy_seed": 50, "attack": "kkt", "feature_extraction": "wordcount", "method": "modify", "bad_loss_percentage": 30, "num_repeats": 5, "accuracy_Train": 95.15, "loss_Train": 0.0037387508219107984, "accuracy_Test": 72.5, "loss_Test": 0.025348577052354812, "benign_accuracy": 0.87875, "attack_success_rate": 1.0}, "poisoning_rate": 0.6, "learning_rate": 0.01, "batch_size": 32, "num_epochs": 500, "data-train": {"name": "training dataset", "num_samples": 2000, "num_features": [200], "class_count": {"0": 405, "1": 1595}}, "data-test": {"name": "testing dataset", "num_samples": 200, "num_features": [200], "class_count": {"0": 106, "1": 94}}, "datetime": "1401-08-01 14:04"}